wenergedatabasemodule/DataUpload.py
wenergedatabasemodule/__init__.py
wenergiedatabasemodule/DataUpload.py
wenergiedatabasemodule/__init__.py
wenergiedatabasemodule-0.1.0.dist-info/LICENSE
wenergiedatabasemodule-0.1.0.dist-info/METADATA
wenergiedatabasemodule-0.1.0.dist-info/WHEEL
wenergiedatabasemodule-0.1.0.dist-info/top_level.txt
wenergiedatabasemodule-0.1.0.dist-info/RECORD
