Metadata-Version: 2.1
Name: wenergiedatabasemodule
Version: 0.1.0
Summary: Module to upload data to database 
Home-page: UNKNOWN
Author: Shinoj cm
Author-email: amshinojcm@gmail.com
License: UNKNOWN
Keywords: python,energy,wenergie,batteryanalytics,database,database
Platform: UNKNOWN
Classifier: Programming Language :: Python :: 3
Classifier: Operating System :: Unix
Classifier: Operating System :: MacOS :: MacOS X
Classifier: Operating System :: Microsoft :: Windows
Requires-Dist: firebase-admin
